{
  "window.title": "SegmentPlayer",
  "group.title": "\u5a92\u4f53\u5206\u7ec4",
  "group.status.valid": "\u53ef\u64ad\u653e",
  "group.status.count": "\u89c6\u9891\u7ec4\u6570\u91cf: {0}",
  "btn.refresh": "\u5237\u65b0",
  "btn.editPlaylist": "\u7f16\u8f91\u987a\u5e8f",
  "btn.settings": "\u8bbe\u7f6e",
  "btn.play": "\u64ad\u653e",
  "btn.edit": "\u7f16\u8f91",
  "btn.back": "\u8fd4\u56de",
  "btn.prevGroup": "\u4e0a\u4e00\u7ec4",
  "btn.prev": "\u4e0a\u4e00\u4e2a",
  "btn.next": "\u4e0b\u4e00\u4e2a",
  "btn.nextGroup": "\u4e0b\u4e00\u7ec4",
  "btn.navigation": "\u5bfc\u822a",
  "btn.toggleMode": "\u5207\u6362 A/M",
  "btn.jump": "\u8df3\u8f6c",
  "btn.cancel": "\u53d6\u6d88",
  "btn.save": "\u4fdd\u5b58",
  "nav.groupPrefix": "\u7ec4",
  "settings.title": "\u8bbe\u7f6e",
  "settings.language": "UI \u8bed\u8a00\uff08\u4e0b\u6b21\u542f\u52a8\u751f\u6548\uff09",
  "settings.groupsRoot": "\u89c6\u9891\u7ec4\u6839\u76ee\u5f55\uff08\u76f8\u5bf9\u5e94\u7528\u76ee\u5f55\uff09",
  "settings.thumbnailFrame": "\u7f29\u7565\u56fe\u5e27\u7d22\u5f15",
  "settings.cacheEnabled": "\u542f\u7528\u7f29\u7565\u56fe\u7f13\u5b58",
  "settings.cacheDir": "\u7f29\u7565\u56fe\u7f13\u5b58\u76ee\u5f55\uff08\u76f8\u5bf9\u5e94\u7528\u76ee\u5f55\uff09",
  "editor.title": "\u64ad\u653e\u987a\u5e8f\u7f16\u8f91",
  "editor.normalize": "\u81ea\u52a8\u91cd\u6392",
  "editor.removeMissing": "\u79fb\u9664\u7f3a\u5931\u9879",
  "editor.missingPrefix": "\u7f3a\u5931",
  "msg.invalid.title": "\u89c6\u9891\u7ec4\u4e0d\u5408\u6cd5",
  "msg.playlist.missing": "\u7f3a\u5c11 playlist.json \u6587\u4ef6\u3002",
  "msg.error.title": "\u9519\u8bef",
  "msg.refresh.nochanges": "\u672a\u68c0\u6d4b\u5230\u53d8\u5316\u3002",
  "msg.refresh.title": "\u5237\u65b0",
  "msg.refresh.added": "\u65b0\u589e\u6761\u76ee",
  "msg.refresh.missing": "\u7f3a\u5931\u6761\u76ee",
  "msg.refresh.prompt": "\u662f\u5426\u66f4\u65b0 playlist\uff1f",
  "settings.saved.restart": "\u5df2\u4fdd\u5b58\uff0c\u8bed\u8a00\u5207\u6362\u5c06\u5728\u4e0b\u6b21\u542f\u52a8\u751f\u6548\u3002",
  "editor.invalid": "\u64ad\u653e\u5217\u8868\u53c2\u6570\u4e0d\u5408\u6cd5\u3002",
  "editor.normalized": "\u5df2\u5b8c\u6210\u81ea\u52a8\u91cd\u6392\u3002",
  "editor.saved": "\u64ad\u653e\u5217\u8868\u5df2\u4fdd\u5b58\u3002"
}
